[
    {
        "Expected": "<SOS> there is a house together with a swimming pool lying at the end of two roads   which is surrounded by forest   bare field and farmland .",
        "Pruned_Predicted": "a building is surrounded by some sparse green trees .",
        "Unpruned_Predicted": "many green trees are in two sides of a curved yellow river ."
    },
    {
        "Expected": "<SOS> a grey building with red cars and a pond is surrounded by many green trees and meadows .",
        "Pruned_Predicted": "a building is surrounded by some sparse green trees .",
        "Unpruned_Predicted": "many green trees are in two sides of a curved yellow river ."
    }
]